factory_server/__init__.py
factory_server/exceptions.py
factory_server/models.py
factory_server/query.py
factory_server/settings.py
podiant_factory_server-0.2.0.dist-info/LICENSE
podiant_factory_server-0.2.0.dist-info/METADATA
podiant_factory_server-0.2.0.dist-info/WHEEL
podiant_factory_server-0.2.0.dist-info/top_level.txt
podiant_factory_server-0.2.0.dist-info/RECORD
