Metadata-Version: 2.1
Name: podiant-factory-server
Version: 0.2.0
Summary: Reliable, asynchronous media workflow manager
Home-page: https://git.steadman.io/podiant/factory-server
Author: Mark Steadman
Author-email: mark@podiant.co
License: MIT
Keywords: podiant-factory-server
Platform: UNKNOWN
Classifier: Development Status :: 3 - Alpha
Classifier: Framework :: Django :: 1.11
Classifier: Intended Audience :: Developers
Classifier: License :: OSI Approved :: BSD License
Classifier: Natural Language :: English
Classifier: Programming Language :: Python :: 3
Classifier: Programming Language :: Python :: 3.4
Classifier: Programming Language :: Python :: 3.5
Classifier: Programming Language :: Python :: 3.6
